co2_mycityco2/__init__.py
co2_mycityco2/cli/__init__.py
co2_mycityco2/cli/cli.py
co2_mycityco2/cli/format.py
co2_mycityco2/const.py
co2_mycityco2/formatter/base.py
co2_mycityco2/formatter/france.py
co2_mycityco2/utils/fr.py
co2_mycityco2-0.2.0.dist-info/METADATA
co2_mycityco2-0.2.0.dist-info/WHEEL
co2_mycityco2-0.2.0.dist-info/RECORD
