Metadata-Version: 2.1
Name: co2_mycityco2
Version: 0.2.0
Summary: 
Author: Adam Bonnet
Author-email: adambonnet0@gmail.com
Requires-Python: >=3.10,<4.0
Classifier: Programming Language :: Python :: 3
Classifier: Programming Language :: Python :: 3.10
Classifier: Programming Language :: Python :: 3.11
Classifier: Programming Language :: Python :: 3.12
Requires-Dist: co2 (>=0.2.2,<0.3.0)
Requires-Dist: typer[all] (>=0.9.0,<0.10.0)
